timezone_converter/__init__.py
timezone_converter/comparison_view.py
timezone_converter/constants.py
timezone_converter/helper.py
timezone_converter/list_view.py
timezone_converter/main.py
timezone_converter/search_view.py
timezone_converter-0.15.0.dist-info/METADATA
timezone_converter-0.15.0.dist-info/WHEEL
timezone_converter-0.15.0.dist-info/entry_points.txt
timezone_converter-0.15.0.dist-info/licenses/LICENSE
timezone_converter-0.15.0.dist-info/RECORD
